music_tonnetztransform/__init__.py
music_tonnetztransform/music_tonnetztransform.py
music_tonnetztransform/neo_riemann_tonnetz.py
music_tonnetztransform-0.1.6.dist-info/licenses/LICENSE
music_tonnetztransform-0.1.6.dist-info/METADATA
music_tonnetztransform-0.1.6.dist-info/WHEEL
music_tonnetztransform-0.1.6.dist-info/top_level.txt
music_tonnetztransform-0.1.6.dist-info/RECORD
