Metadata-Version: 2.4
Name: music_tonnetztransform
Version: 0.1.6
Summary: Perform Neo-Riemann operations on musical chords
Author-email: Gene Boggs <gene.boggs@gmail.com>
License:                     GNU GENERAL PUBLIC LICENSE
Project-URL: Homepage, https://github.com/ology/Python-Music-TonnetzTransform
Project-URL: Repository, https://github.com/ology/Python-Music-TonnetzTransform.git
Project-URL: Issues, https://github.com/ology/Python-Music-TonnetzTransform/issues
Classifier: Development Status :: 2 - Pre-Alpha
Classifier: Programming Language :: Python
Classifier: Programming Language :: Python :: 3
Classifier: Programming Language :: Python :: 3.9
Classifier: Programming Language :: Python :: 3.10
Classifier: Programming Language :: Python :: 3.11
Classifier: Programming Language :: Python :: 3.12
Requires-Python: >=3.9
License-File: LICENSE
Requires-Dist: itertools
Requires-Dist: music21
Requires-Dist: music_melodicdevice
Dynamic: license-file
